benchmark_simulator/__init__.py
benchmark_simulator/_constants.py
benchmark_simulator/_secure_proc.py
benchmark_simulator/_utils.py
benchmark_simulator/simulator.py
benchmark_simulator/_simulator/_base_wrapper.py
benchmark_simulator/_simulator/_utils.py
benchmark_simulator/_simulator/_worker.py
benchmark_simulator/_simulator/_worker_manager.py
benchmark_simulator/_simulator/_worker_manager_for_ask_and_tell.py
benchmark_simulator/_trackers/_config_tracker.py
benchmark_simulator/_trackers/_state_tracker.py
benchmark_simulator/utils/__init__.py
benchmark_simulator/utils/_performance_over_time.py
mfhpo_simulator-1.4.6.dist-info/LICENSE
mfhpo_simulator-1.4.6.dist-info/METADATA
mfhpo_simulator-1.4.6.dist-info/WHEEL
mfhpo_simulator-1.4.6.dist-info/top_level.txt
mfhpo_simulator-1.4.6.dist-info/RECORD
