Metadata-Version: 2.1
Name: mfhpo-simulator
Version: 1.4.6
Home-page: https://github.com/nabenabe0928/mfhpo-simulator
Author: nabenabe0928
Author-email: shuhei.watanabe.utokyo@gmail.com
Platform: Linux
Platform: Darwin
Requires-Python: >=3.8
License-File: LICENSE
Requires-Dist: ujson
Requires-Dist: numpy
Requires-Dist: scipy
